cjm_transcription_plugin_system/__init__.py
cjm_transcription_plugin_system/_modidx.py
cjm_transcription_plugin_system/core.py
cjm_transcription_plugin_system/plugin_interface.py
cjm_transcription_plugin_system-0.0.9.dist-info/licenses/LICENSE
cjm_transcription_plugin_system-0.0.9.dist-info/METADATA
cjm_transcription_plugin_system-0.0.9.dist-info/WHEEL
cjm_transcription_plugin_system-0.0.9.dist-info/entry_points.txt
cjm_transcription_plugin_system-0.0.9.dist-info/top_level.txt
cjm_transcription_plugin_system-0.0.9.dist-info/RECORD
