Metadata-Version: 2.4
Name: cjm-transcription-plugin-system
Version: 0.0.9
Summary: A flexible plugin system for audio transcription intended to make it easy to add support for multiple backends.
Home-page: https://github.com/cj-mills/cjm-transcription-plugin-system
Author: Christian J. Mills
Author-email: 9126128+cj-mills@users.noreply.github.com
License: Apache Software License 2.0
Keywords: nbdev jupyter notebook python
Classifier: Development Status :: 4 - Beta
Classifier: Intended Audience :: Developers
Classifier: Natural Language :: English
Classifier: Programming Language :: Python :: 3.11
Classifier: Programming Language :: Python :: 3.12
Classifier: License :: OSI Approved :: Apache Software License
Requires-Python: >=3.11
License-File: LICENSE
Requires-Dist: nbdev
Requires-Dist: numpy
Requires-Dist: jsonschema
Requires-Dist: cjm_plugin_system
Provides-Extra: dev
Dynamic: author
Dynamic: author-email
Dynamic: classifier
Dynamic: description
Dynamic: description-content-type
Dynamic: home-page
Dynamic: keywords
Dynamic: license
Dynamic: license-file
Dynamic: provides-extra
Dynamic: requires-dist
Dynamic: requires-python
Dynamic: summary
